MANIFEST.in
README.rst
setup.py
django_admin_dialog/__init__.py
django_admin_dialog/admin.py
django_admin_dialog/context_processors.py
django_admin_dialog/mixins.py
django_admin_dialog/models.py
django_admin_dialog/settings.py
django_admin_dialog.egg-info/PKG-INFO
django_admin_dialog.egg-info/SOURCES.txt
django_admin_dialog.egg-info/dependency_links.txt
django_admin_dialog.egg-info/requires.txt
django_admin_dialog.egg-info/top_level.txt
django_admin_dialog/migrations/0001_initial.py
django_admin_dialog/migrations/__init__.py
django_admin_dialog/static/django_admin_dialog/css/jquery-ui.css
django_admin_dialog/static/django_admin_dialog/css/jquery-ui.structure.css
django_admin_dialog/static/django_admin_dialog/css/jquery-ui.theme.css
django_admin_dialog/static/django_admin_dialog/css/images/ui-bg_flat_0_aaaaaa_40x100.png
django_admin_dialog/static/django_admin_dialog/css/images/ui-bg_flat_55_fbec88_40x100.png
django_admin_dialog/static/django_admin_dialog/css/images/ui-bg_glass_75_d0e5f5_1x400.png
django_admin_dialog/static/django_admin_dialog/css/images/ui-bg_glass_85_dfeffc_1x400.png
django_admin_dialog/static/django_admin_dialog/css/images/ui-bg_glass_95_fef1ec_1x400.png
django_admin_dialog/static/django_admin_dialog/css/images/ui-bg_gloss-wave_55_5c9ccc_500x100.png
django_admin_dialog/static/django_admin_dialog/css/images/ui-bg_inset-hard_100_f5f8f9_1x100.png
django_admin_dialog/static/django_admin_dialog/css/images/ui-bg_inset-hard_100_fcfdfd_1x100.png
django_admin_dialog/static/django_admin_dialog/css/images/ui-icons_217bc0_256x240.png
django_admin_dialog/static/django_admin_dialog/css/images/ui-icons_2e83ff_256x240.png
django_admin_dialog/static/django_admin_dialog/css/images/ui-icons_469bdd_256x240.png
django_admin_dialog/static/django_admin_dialog/css/images/ui-icons_6da8d5_256x240.png
django_admin_dialog/static/django_admin_dialog/css/images/ui-icons_cd0a0a_256x240.png
django_admin_dialog/static/django_admin_dialog/css/images/ui-icons_d8e7f3_256x240.png
django_admin_dialog/static/django_admin_dialog/css/images/ui-icons_f9bd01_256x240.png
django_admin_dialog/static/django_admin_dialog/images/information.png
