Metadata-Version: 1.1
Name: django-admin-dialog
Version: 1.0.8
Summary: Shows a dialog popup with helptext for the admin fields that you have indicated.
Home-page: https://github.com/quiqueporta/django-admin-dialog
Author: Quique Porta
Author-email: quiqueporta@gmail.com
License: GPLv2
Download-URL: https://github.com/quiqueporta/django-admin-dialog/releases
Keywords: django,tools
Platform: UNKNOWN
Classifier: Development Status :: 5 - Production/Stable
Classifier: Environment :: Web Environment
Classifier: Framework :: Django
Classifier: Intended Audience :: Developers
Classifier: License :: OSI Approved :: GNU Lesser General Public License v2 (LGPLv2)
Classifier: Natural Language :: English
Classifier: Operating System :: OS Independent
Classifier: Programming Language :: Python
Classifier: Topic :: Internet :: WWW/HTTP
